{
  "index": [
    {
      "id": "root",
      "type": "folder",
      "title": "Pages",
      "children": [
        {
          "id": "folder-1762575430654",
          "type": "folder",
          "title": "New Folder",
          "children": []
        }
      ]
    }
  ],
  "docs": {},
  "comments": {},
  "history": {},
  "users": {},
  "syncMeta": {
    "lastSync": "2025-11-08T04:26:29.032Z",
    "dirty": true,
    "remoteSha": "042c3abe23f43253230d09ccc508dadd1d688353",
    "conflicts": []
  }
}